llama_index/llms/anyscale/__init__.py
llama_index/llms/anyscale/base.py
llama_index/llms/anyscale/utils.py
llama_index_llms_anyscale-0.4.2.dist-info/METADATA
llama_index_llms_anyscale-0.4.2.dist-info/WHEEL
llama_index_llms_anyscale-0.4.2.dist-info/licenses/LICENSE
llama_index_llms_anyscale-0.4.2.dist-info/RECORD
